debx/__init__.py
debx/__main__.py
debx/ar.py
debx/builder.py
debx/deb822.py
debx/py.typed
debx/reader.py
debx/cli/__init__.py
debx/cli/inspect.py
debx/cli/pack.py
debx/cli/sign.py
debx/cli/types.py
debx/cli/unpack.py
debx-0.2.12.dist-info/METADATA
debx-0.2.12.dist-info/WHEEL
debx-0.2.12.dist-info/entry_points.txt
debx-0.2.12.dist-info/licenses/COPYING
debx-0.2.12.dist-info/RECORD
