Metadata-Version: 2.4
Name: debx
Version: 0.2.10
Summary: Minimal Python library to programmatically construct Debian .deb packages
Author-email: Dmitry Orlov <me@mosquito.su>
License-Expression: MIT
Project-URL: Homepage, https://github.com/mosquito/debx
Project-URL: Repository, https://github.com/mosquito/debx
Project-URL: Issues, https://github.com/mosquito/debx/issues
Project-URL: Documentation, https://github.com/mosquito/debx/wiki
Classifier: Development Status :: 3 - Alpha
Classifier: Intended Audience :: Developers
Classifier: Programming Language :: Python :: 3
Classifier: Programming Language :: Python :: 3.10
Classifier: Programming Language :: Python :: 3.11
Classifier: Programming Language :: Python :: 3.12
Classifier: Programming Language :: Python :: 3.13
Classifier: Programming Language :: Python :: 3.14
Classifier: Topic :: Software Development :: Build Tools
Classifier: Typing :: Typed
Requires-Python: >=3.10
License-File: COPYING
Dynamic: license-file
